README.md
setup.py
instaboost/InstaBoost.py
instaboost/__init__.py
instaboost/affine_transform.py
instaboost/config.py
instaboost/exceptions.py
instaboost/get_instance_group.py
instaboost/help_functions.py
instaboost/pointByHeatmap.py
instaboost/pycococreater.py
instaboost/single_image_process.py
instaboost.egg-info/PKG-INFO
instaboost.egg-info/SOURCES.txt
instaboost.egg-info/dependency_links.txt
instaboost.egg-info/requires.txt
instaboost.egg-info/top_level.txt