Metadata-Version: 1.0
Name: instaboost
Version: 0.2
Summary: a python implementation for paper: "InstaBoost: Boosting Instance Segmentation Via Probability Map GuidedCopy-Pasting"
Home-page: https://github.com/GothicAi/InstaBoost-pypi
Author: Haoshu Fang, Jianhua Sun, Runzhong Wang,  Minghao Gou, Yonglu Li, Cewu Lu
Author-email: 1751196720@qq.com
License: UNKNOWN
Platform: UNKNOWN
